{
  "type": "object",
  "required": [
    "OrganizationId",
    "EntityId"
  ],
  "name": "DeregisterFromWorkMailRequest",
  "properties": {
    "OrganizationId": {
      "allOf": [
        {
          "$ref": "#/components/schemas/OrganizationId"
        },
        {
          "description": "The identifier for the organization under which the WorkMail entity exists."
        }
      ]
    },
    "EntityId": {
      "allOf": [
        {
          "$ref": "#/components/schemas/WorkMailIdentifier"
        },
        {
          "description": "The identifier for the member (user or group) to be updated."
        }
      ]
    }
  },
  "$schema": "https://json-structure.org/meta/core/v0/#",
  "$id": "https://raw.githubusercontent.com/api-evangelist/amazon-workmail/refs/heads/main/json-structure/workmail-deregister-from-work-mail-request-structure.json",
  "description": "DeregisterFromWorkMailRequest schema from Amazon WorkMail API"
}